Workbook

Sheet Bahia Blanca
A3: CLIENTE : | B3: XX
A5: BUQUE :
A8: BAHIA BLANCA
A9: PUERTO
A10: TERMINAL
A11: CF | B11: 185
A12: TRN | B12: 27581
A13: CARGA | B13: 22000
A14: SLORA | B14: 229
A17: PORT DUES BB | D17: PORT DUES BB
A18: TRN | B18: DIAS | D18: HORA | E18: ENTRADA | F18: SALIDA
A19: =+B12 -> 27581 | B19: 2 | D19: 00:00 a 08:00 | E19: 1 | F19: 0.33
A20: =+A19*0.46*B19 -> 25374.52 | D20: 08:00 a 16:00 | E20: 0.67 | F20: 0.67
D21: 16:00 a 24:00 | E21: 0.33 | F21: 1
H22: BUNKER (Fondadero)
H23: TRN | I23: =B12 -> 27581
D24: TOLL DUES BB | H24: =I23*0.15*B19 -> 8274.3
A25: TOLL DUES BB | D25: 5000 | F25: 0.6
A26: CANT CARGADA | D26: 5000 | E26: 10000 | F26: 0.85
A27: 22000 | D27: 10000 | E27: 17000 | F27: 1
A28: =IF(B12<=5000,(A27*1.55*F25+A27*0.5*F25),IF(B12<=10000,(A27*1.55*F26+A27*0.5*F26),IF(B12<=17000,(A27*1.55*F27+A27*0.5*F27),IF(B12<=24000,(A27*1.55*F28+A27*0.5*F28),IF(B12>24000,(A27*1.55*F29+A27*0.5*F29),0))))) -> 51865 | D28: 17000 | E28: 24000 | F28: 1.15
D29: 24000 | F29: 1.15
A34: PORT PILOTS
B35: PIES | C35: MTS
A36: ENTRADA | B36: 0 | C36: =+B36*0.3048 -> 0
A37: SALIDA | B37: 0 | C37: =+B37*0.3048 -> 0
B40: PRACTICOS PUERTO BB
B41: BOYA 11 | D41: GALVAN | F41: ROSALES
A42: SERVICIO | B42: =IF(C36<=8.53,(+B11*14+B11*8+53*12)*0,IF(C36<=9.14,(+B11*14+B11*8+53*12)*H49,IF(C36<=9.75,(+B11*14+B11*8+53*12)*H50,IF(C36>9.76,(+B11*14+B11*8+53*12)*H50,0))))+(+B11*14+B11*8+53*12) -> 4706 | C42: =IF(C37<=8.53,(+B11*14+B11*8+53*12)*0,IF(C37<=9.14,(+B11*14+B11*8+53*12)*H49,IF(C37<=9.75,(+B11*14+B11*8+53*12)*H50,IF(C37>9.76,(+B11*14+B11*8+53*12)*H50,0))))+(+B11*14+B11*8+53*12) -> 4706 | D42: =IF(C36<=8.53,(+B11*14+B11*8+55*12)*0,IF(C36<=9.14,(+B11*14+B11*8+55*12)*H49,IF(C36<=9.75,(+B11*14+B11*8+55*12)*H50,IF(C36>9.76,(+B11*14+B11*8+55*12)*H50,0))))+(+B11*14+B11*8+55*12) -> 4730 | E42: =IF(C37<=8.53,(+B11*14+B11*8+55*12)*0,IF(C37<=9.14,(+B11*14+B11*8+55*12)*H49,IF(C37<=9.75,(+B11*14+B11*8+55*12)*H50,IF(C37>9.76,(+B11*14+B11*8+55*12)*H50,0))))+(+B11*14+B11*8+55*12) -> 4730 | F42: =IF(C36<=8.53,(+B11*14+B11*8+25*12)*0,IF(C36<=9.14,(+B11*14+B11*8+25*12)*H49,IF(C36<=9.75,(+B11*14+B11*8+25*12)*H50,IF(C36>9.76,(+B11*14+B11*8+25*12)*H50,0))))+(+B11*14+B11*8+25*12) -> 4370 | G42: =IF(C37<=8.53,(+B11*14+B11*8+25*12)*0,IF(C37<=9.14,(+B11*14+B11*8+25*12)*H49,IF(C37<=9.75,(+B11*14+B11*8+25*12)*H50,IF(C37>9.76,(+B11*14+B11*8+25*12)*H50,0))))+(+B11*14+B11*8+25*12) -> 4370
A43: CONEXO | B43: 6064 | C43: 6064 | D43: 6064 | E43: 6064 | F43: 6064 | G43: 6064
A44: TOTAL | B44: =+B42+B43 -> 10770 | C44: =+C42+C43 -> 10770 | D44: =+D42+D43 -> 10794 | E44: =+E42+E43 -> 10794 | F44: =+F42+F43 -> 10434 | G44: =+G42+G43 -> 10434
B45: =+B44+C44 -> 21540 | D45: =+D44+E44 -> 21588 | F45: =+F44+G44 -> 20868
A46: NC | B46: =B43*12% -> 727.68 | C46: =C43*12% -> 727.68 | D46: =D43*12% -> 727.68 | E46: =E43*12% -> 727.68 | F46: =F43*12% -> 727.68 | G46: =G43*12% -> 727.68
B48: DISTANCIAS
B49: BOYA 11 - ROSALES | D49: 25 | F49: 8.53 | G49: 9.14 | H49: 0.075
B50: BOYA 11 - WHITE | D50: 53 | F50: 9.14 | G50: 9.75 | H50: 0.15
B51: BOYA 11 - GALVAN | D51: 55 | F51: Cofco 10% sobre el serv + 15% sobre conex

Sheet Ajustada
C8: From 18-03-26 to 20-03-26
B9: Initial | C9: Close to Real
A10: VESSEL | B10: HAOYUE | C10: =B10 -> HAOYUE
A11: PORT | B11: BAHIA BLANCA | C11: BAHIA BLANCA
A12: BERTH | B12: ADM | C12: ADM
A13: PERMANENCY | B13: 2 days | C13: 2 days
A14: CURRENCY | B14: USD | C14: USD
A15: ITEM | B15: AMOUNT | C15: AMOUNT
A16: Port dues | B16: 25375 | C16: ='Bahia Blanca'!A20 -> 25374.52 | E16: Proviene de San Lorenzo
A17: Toll dues | B17: 51865 | C17: ='Bahia Blanca'!A28 -> 51865 | E17: Remolcadores Pto Mariel
A18: Port pilotage | B18: 22952 | C18: =22800 -> 22800 | E18: 2 de Entrada / 2 de Salida
A19: Mooring & unmooring services | B19: 5643 | C19: 6890 | E19: Diferencia con Advance usd 37.000
A20: Towage services | B20: 12150 | C20: 16200
A21: Custom house expenses | B21: 200 | C21: 600
A22: Migration expenses - outward | B22: 1250 | C22: 1250
A23: Garbage compulsory inspection | B23: 96 | C23: 4
A24: Watchmen compulsory services | B24: 3000 | C24: =3406*0.9 -> 3065.4
A25: Headclerk compulsory services | B25: 4400 | C25: =2708*0.9 -> 2437.2
A26: OSRO Coverage for bunkers | B26: 2880 | C26: 1980
A27: Custom house bunkering | C27: 400
A28: Agency fee | B28: 2000 | C28: 2000
A30: TOTAL | B30: =SUM(B16:B28) -> 131811 | C30: =SUM(C16:C28) -> 134866.12
A32: Our bank account
A33: CITIBANK NA, NY BRANCH 111 WALL STREET / NEW YORK, 10043
A34: ABA: 21000089 / SWIFT: CITIUS33 / ACCOUNT NO:36404074
A35: BENEFICIARY: Independent Ship Agents SA
A36: In order to avoid double income taxation on gross freight, which is equivalent to aproximate 3.5 pct, you must provide us with a tax affidavit. Please let us know if you need assitance on this.
A41: Please note that this is a pro-forma disbursement account only. It is intended to be an estimate of the actual disbursement account and is for guidance purposes only. Whilst does take every care to ensure that the figures and information contained in the pro-forma disbursement account are as accurate as possible, the actual disbursement account may, and often does, for various reasons beyond our control, vary from the pro-forma disbursement account. You are required and liable to pay upon demand, the full amount described and shown in the actual disbursement account. This duty exists regardless of any difference betweeen the figures in this pro-forma disbursement account and the actual disbursement account. For the avoidance of doubt, this pro-forma disbursement account is not a contractual document.

Sheet Breakdown
E4: ='Bahia Blanca'!B5 -> 0
B10: Port dues
C12: =_xlfn.CONCAT("Port ","BAHIA BLANCA"," - Terminal ",'Bahia Blanca'!B10) -> Port BAHIA BLANCA - Terminal
C13: ='Bahia Blanca'!B12 -> 27581 | D13: TRN*0,46* | E13: =_xlfn.CONCAT('Bahia Blanca'!B19," days at port") -> 2 days at port | G13: ='Bahia Blanca'!A20 -> 25374.52
F16: TOTAL USD | G16: =G13 -> 25374.52
B21: Toll dues
B22: Includes retribution for the maintenance of external and internal navigation channel depth used for the navigation of the vessel.
D24: TONS X 1,55 X Ft + TONS X 0.40 X Ft
D26: ='Bahia Blanca'!A27 -> 22000 | E26: * 1,55 * | F26: {=_xlfn.IFS('Bahia Blanca'!A27<5000,0.6,'Bahia Blanca'!A27<=10000,0.85,'Bahia Blanca'!A27<=17000,1,'Bahia Blanca'!A27<=30000,1.15)} -> 1.15 | G26: =_xlfn.CONCAT("* ",D26) -> * 22000 | H26: * 0,4 * | I26: =F26 -> 1.15 | J26: =_xlfn.CONCAT("= ",'Bahia Blanca'!A28) -> = 51865
B28: TONS=Gross tons loading or discharge of the vessel
B29: Ft = Vessel capacity Coefficient ( see chart below)
B31: Coefficient for vessel capacity (Ft):
B33: TRN | F33: Ft
B34: Less than 5.000 | F34: 0.6
B35: More than 5.000 to 10.000 inclusive | F35: 0.85
B36: More than 10.000 to 17.000 inclusive | F36: 1
B37: More than 17.000 to 24.000 inclusive | F37: 1.15
B38: More than 24.000 | F38: 1.15
B42: Bunker operation:
B43: TRN 20% * 1.35 *USD 0.90 * 1.15
B44: Base: Per gross ton or fraction loaded or discharged by the ship, with consideration of the draft and the capacity of the ship.
B49: Port pilotage
B51: Tariffs for entrance or sailing:
B52: B.T. (basic tariff) =( (Fiscal unit tariff 14 * Vessel's Fiscal Coefficient) + (Fiscal unit tariff 8 * Vessel's Fiscal Coefficient) (Fiscal unit tariff 12 * N km travelled )) + % Exceeding draft if more than 28 feets
C55: ( 14 * | D55: =_xlfn.CONCAT('Bahia Blanca'!B11," ) "," + ") -> 185 ) + | E55: ( 8 * | F55: =D55 -> 185 ) + | G55: {=_xlfn.IFS('Bahia Blanca'!B10='Bahia Blanca'!B41,"+ (12 * 53)",'Bahia Blanca'!B10='Bahia Blanca'!D41,"+ (12 * 55)",'Bahia Blanca'!B10='Bahia Blanca'!F41,"+ (12 * 25)")} -> #N/A | H55: * 1,15 | I55: = | J55: USD | K55: =IF('Bahia Blanca'!B10='Bahia Blanca'!B41,'Bahia Blanca'!B42,IF('Bahia Blanca'!B10='Bahia Blanca'!D41,'Bahia Blanca'!D42,IF('Bahia Blanca'!B10='Bahia Blanca'!F41,'Bahia Blanca'!F42,0))) -> 0
B58: Vessel’s Fiscal Coefficient: (Length Overall * Extreme Breadth * Depth Overall)/800
C60: Destination | F60: Km
C61: Buoy 11 - Pto Rosales | F61: 25
C62: Buoy 11 - Ing White | F62: 53
C63: Buoy 11 - Pto Galvan | F63: 55
B66: Connected services ( Transportation + Pilots boats ) | H66: USD 6064

Sheet Calculos
A1: XX
A2: GOLDEN OCEAN GROUP
A3: ADM
A4: AMAGGI
A5: ARASCO
A6: AXLE MARINE SINGAPURE
A7: BALKAN AND BLACK SEA
A8: BALTNAV
A9: BERGE
A10: BOLTEN
A11: CANAL ROJO
A12: CARGILL
... A59: WL MANAGEMENT
