Workbook

Sheet Bahia Blanca
A3: CLIENTE : | B3: XX
A5: BUQUE :
A8: BAHIA BLANCA
A9: PUERTO
A10: TERMINAL
A11: CF | B11: 150
A12: TRN | B12: 20209
A13: CARGA | B13: 0
A14: SLORA | B14: 199.98
A17: PORT DUES BB | D17: PORT DUES BB
A18: TRN | B18: DIAS | D18: HORA | E18: ENTRADA | F18: SALIDA
A19: =+B12 -> 20209 | B19: 1.33 | D19: 00:00 a 08:00 | E19: 1 | F19: 0.33
A20: =+A19*0.46*B19 -> 12363.866 | D20: 08:00 a 16:00 | E20: 0.67 | F20: 0.67
D21: 16:00 a 24:00 | E21: 0.33 | F21: 1
H22: BUNKER (Fondadero)
H23: TRN | I23: =B12 -> 20209
D24: TOLL DUES BB | H24: =I23*0.15*B19 -> 4031.6955
A25: TOLL DUES BB | D25: 5000 | F25: 0.6
A26: CANT CARGADA | D26: 5000 | E26: 10000 | F26: 0.85
A27: 12050 | D27: 10000 | E27: 17000 | F27: 1
A28: =IF(B12<=5000,(A27*1.55*F25+A27*0.5*F25),IF(B12<=10000,(A27*1.55*F26+A27*0.5*F26),IF(B12<=17000,(A27*1.55*F27+A27*0.5*F27),IF(B12<=24000,(A27*1.55*F28+A27*0.5*F28),IF(B12>24000,(A27*1.55*F29+A27*0.5*F29),0))))) -> 28407.875 | D28: 17000 | E28: 24000 | F28: 1.15
D29: 24000 | F29: 1.15
A34: PORT PILOTS
B35: PIES | C35: MTS
A36: ENTRADA | B36: 0 | C36: =+B36*0.3048 -> 0
A37: SALIDA | B37: 0 | C37: =+B37*0.3048 -> 0
B40: PRACTICOS PUERTO BB
B41: BOYA 11 | D41: GALVAN | F41: ROSALES
A42: SERVICIO | B42: =IF(C36<=8.53,(+B11*14+B11*8+53*12)*0,IF(C36<=9.14,(+B11*14+B11*8+53*12)*H49,IF(C36<=9.75,(+B11*14+B11*8+53*12)*H50,IF(C36>9.76,(+B11*14+B11*8+53*12)*H50,0))))+(+B11*14+B11*8+53*12) -> 3936 | C42: =IF(C37<=8.53,(+B11*14+B11*8+53*12)*0,IF(C37<=9.14,(+B11*14+B11*8+53*12)*H49,IF(C37<=9.75,(+B11*14+B11*8+53*12)*H50,IF(C37>9.76,(+B11*14+B11*8+53*12)*H50,0))))+(+B11*14+B11*8+53*12) -> 3936 | D42: =IF(C36<=8.53,(+B11*14+B11*8+55*12)*0,IF(C36<=9.14,(+B11*14+B11*8+55*12)*H49,IF(C36<=9.75,(+B11*14+B11*8+55*12)*H50,IF(C36>9.76,(+B11*14+B11*8+55*12)*H50,0))))+(+B11*14+B11*8+55*12) -> 3960 | E42: =IF(C37<=8.53,(+B11*14+B11*8+55*12)*0,IF(C37<=9.14,(+B11*14+B11*8+55*12)*H49,IF(C37<=9.75,(+B11*14+B11*8+55*12)*H50,IF(C37>9.76,(+B11*14+B11*8+55*12)*H50,0))))+(+B11*14+B11*8+55*12) -> 3960 | F42: =IF(C36<=8.53,(+B11*14+B11*8+25*12)*0,IF(C36<=9.14,(+B11*14+B11*8+25*12)*H49,IF(C36<=9.75,(+B11*14+B11*8+25*12)*H50,IF(C36>9.76,(+B11*14+B11*8+25*12)*H50,0))))+(+B11*14+B11*8+25*12) -> 3600 | G42: =IF(C37<=8.53,(+B11*14+B11*8+25*12)*0,IF(C37<=9.14,(+B11*14+B11*8+25*12)*H49,IF(C37<=9.75,(+B11*14+B11*8+25*12)*H50,IF(C37>9.76,(+B11*14+B11*8+25*12)*H50,0))))+(+B11*14+B11*8+25*12) -> 3600
A43: CONEXO | B43: 6064 | C43: 6064 | D43: 6064 | E43: 6064 | F43: 6064 | G43: 6064
A44: TOTAL | B44: =+B42+B43 -> 10000 | C44: =+C42+C43 -> 10000 | D44: =+D42+D43 -> 10024 | E44: =+E42+E43 -> 10024 | F44: =+F42+F43 -> 9664 | G44: =+G42+G43 -> 9664
B45: =+B44+C44 -> 20000 | D45: =+D44+E44 -> 20048 | F45: =+F44+G44 -> 19328
A46: NC | B46: =B43*12% -> 727.68 | C46: =C43*12% -> 727.68 | D46: =D43*12% -> 727.68 | E46: =E43*12% -> 727.68 | F46: =F43*12% -> 727.68 | G46: =G43*12% -> 727.68
B48: DISTANCIAS
B49: BOYA 11 - ROSALES | D49: 25 | F49: 8.53 | G49: 9.14 | H49: 0.075
B50: BOYA 11 - WHITE | D50: 53 | F50: 9.14 | G50: 9.75 | H50: 0.15
B51: BOYA 11 - GALVAN | D51: 55 | F51: Cofco 10% sobre el serv + 15% sobre conex

Sheet Ajustada
C8: From 18-01-26 to 20-01-26
B9: Initial | C9: Close to Real
A10: VESSEL | B10: RED AZALEA | C10: RED AZALEA
A11: PORT | B11: BAHIA BLANCA | C11: BAHIA BLANCA
A12: BERTH | B12: TBBCA 9 | C12: ADM
A13: PERMANENCY | B13: 2 days | C13: 1,33 days
A14: CURRENCY | B14: USD | C14: USD
A15: ITEM | B15: AMOUNT | C15: AMOUNT
A16: Port dues | B16: 18592 | C16: ='Bahia Blanca'!A20 -> 12363.866
A17: Toll dues | B17: 40078 | C17: ='Bahia Blanca'!A28 -> 28407.875
A18: Port pilotage | B18: 21181 | C18: 21181
A19: Mooring & unmooring services | B19: 5643 | C19: 5643
A20: Mooring & unmooring services - Overtime | C20: 5287
A21: Towage services | B21: 12150 | C21: 12150
A22: Custom house expenses | B22: 200 | C22: 400
A23: Custom house Permanence | C23: 400
A24: Migration expenses - outward | B24: 1250 | C24: 1300
A25: Garbage compulsory inspection | B25: 96 | C25: 4
A26: Watchmen compulsory services | C26: 3179
A27: Headclerk compulsory services | B27: 4500 | C27: =1241*0.9 -> 1116.9
A28: Full on hire bunker survey | C28: 1070
A29: OSRO Annex 18 | C29: 1980
A30: Custom house bunkering | C30: 600
A31: Agency fee | B31: 2000 | C31: 2000
A33: TOTAL | B33: =SUM(B16:B31) -> 105690 | C33: =SUM(C16:C31) -> 97082.641
A35: Our bank account
A36: CITIBANK NA, NY BRANCH 111 WALL STREET / NEW YORK, 10043
A37: ABA: 21000089 / SWIFT: CITIUS33 / ACCOUNT NO:36404074
A38: BENEFICIARY: Independent Ship Agents SA
A39: In order to avoid double income taxation on gross freight, which is equivalent to aproximate 3.5 pct, you must provide us with a tax affidavit. Please let us know if you need assitance on this.
A44: Please note that this is a pro-forma disbursement account only. It is intended to be an estimate of the actual disbursement account and is for guidance purposes only. Whilst does take every care to ensure that the figures and information contained in the pro-forma disbursement account are as accurate as possible, the actual disbursement account may, and often does, for various reasons beyond our control, vary from the pro-forma disbursement account. You are required and liable to pay upon demand, the full amount described and shown in the actual disbursement account. This duty exists regardless of any difference betweeen the figures in this pro-forma disbursement account and the actual disbursement account. For the avoidance of doubt, this pro-forma disbursement account is not a contractual document.

Sheet Financiero
B2: Lanchas de Glatil + CARP NO FORMAN PARTE DEL DESCUENTO | F2: 0.1 | H2: ROE CCL | I2: 1100
H3: ROE OFFICIAL | I3: 1058
H4: ROE AGP | I4: 1080 | J4: *Billete vendedor
B5: ITEMS | C5: MONTOS NETO | D5: MONTOS BRUTOS | E5: ROE | F5: % | G5: ER DIFFERENTIAL | H5: ISA COMMISION | I5: NET PDA
B6: PORT DUES | C6: =Ajustada!C16 -> 12363.866 | E6: =$I$3 -> 1058 | F6: =+$E6/$I$2-1 -> -0.038181818 | G6: =+C6*F6 -> -472.07489 | H6: =-(G6)*$F$2 -> 47.207489 | I6: =C6+G6+H6 -> 11938.999
B7: TOLL DUES | C7: =Ajustada!C17 -> 28407.875 | E7: =$I$3 -> 1058 | F7: =+$E7/$I$2-1 -> -0.038181818 | G7: =+C7*F7 -> -1084.6643 | H7: =-(G7)*$F$2 -> 108.46643 | I7: =C7+G7+H7 -> 27431.677
B8: PORT PILOTAGE | C8: =Ajustada!C18 -> 21181 | E8: =$I$3 -> 1058 | F8: =+$E8/$I$2-1 -> -0.038181818 | G8: =+C8*F8 -> -808.72909 | H8: =-(G8)*$F$2 -> 80.872909 | I8: =C8+G8+H8 -> 20453.144
B9: MOORING EXPENSES | C9: =Ajustada!C19 -> 5643 | E9: =$I$3 -> 1058 | F9: =+$E9/$I$2-1 -> -0.038181818 | G9: =+C9*F9 -> -215.46 | H9: =-(G9)*$F$2 -> 21.546 | I9: =C9+G9+H9 -> 5449.086
B10: CUSTOM HOUSE EXPENSES | C10: =Ajustada!C21 -> 12150 | E10: =$I$3 -> 1058 | F10: =+$E10/$I$2-1 -> -0.038181818 | G10: =+C10*F10 -> -463.90909 | H10: =-(G10)*$F$2 -> 46.390909 | I10: =C10+G10+H10 -> 11732.482
B11: MIGRATION EXPENSES | C11: =Ajustada!C22 -> 400 | E11: =$I$3 -> 1058 | F11: =+$E11/$I$2-1 -> -0.038181818 | G11: =+C11*F11 -> -15.272727 | H11: =-(G11)*$F$2 -> 1.5272727 | I11: =C11+G11+H11 -> 386.25455
B12: SANITARY DUES | C12: =Ajustada!C23 -> 400 | E12: =$I$3 -> 1058 | F12: =+$E12/$I$2-1 -> -0.038181818 | G12: =+C12*F12 -> -15.272727 | H12: =-(G12)*$F$2 -> 1.5272727 | I12: =C12+G12+H12 -> 386.25455
B13: GARBAGE COMPULSORY INSPECTION | C13: =Ajustada!C24 -> 1300 | E13: =$I$3 -> 1058 | F13: =+$E13/$I$2-1 -> -0.038181818 | G13: =+C13*F13 -> -49.636364 | H13: =-(G13)*$F$2 -> 4.9636364 | I13: =C13+G13+H13 -> 1255.3273
B14: WATCHMEN COMPULSORY SERVICES | C14: =Ajustada!#REF! -> #REF! | E14: =$I$3 -> 1058 | F14: =+$E14/$I$2-1 -> -0.038181818 | G14: =+C14*F14 -> #REF! | H14: =-(G14)*$F$2 -> #REF! | I14: =C14+G14+H14 -> #REF!
B15: HEADCLERK COMPULSORY SERVICES | C15: =Ajustada!C25 -> 4 | E15: =$I$3 -> 1058 | F15: =+$E15/$I$2-1 -> -0.038181818 | G15: =+C15*F15 -> -0.15272727 | H15: =-(G15)*$F$2 -> 0.015272727 | I15: =C15+G15+H15 -> 3.8625455
B16: MISCELLANEOUS | C16: =Ajustada!C26 -> 3179 | E16: =$I$3 -> 1058 | F16: =+$E16/$I$2-1 -> -0.038181818 | G16: =+C16*F16 -> -121.38 | H16: =-(G16)*$F$2 -> 12.138 | I16: =C16+G16+H16 -> 3069.758
B17: TAX ON CREDIT/DEBIT LAW 25.413 | C17: =SUM(C6:C16)*0.012 -> #REF! | E17: =$I$3 -> 1058 | F17: =+$E17/$I$2-1 -> -0.038181818 | G17: =+C17*F17 -> #REF! | H17: =-(G17)*$F$2 -> #REF! | I17: =C17+G17+H17 -> #REF!
B18: TOTAL | C18: =SUM(C6:C17) -> #REF! | G18: =SUM(G6:G17) -> #REF! | H18: =SUM(H6:H17) -> #REF! | I18: =SUM(I6:I17) -> #REF!
B19: Total sin considerar Carp + Glatil | C19: =SUM(C6:C17) -> #REF!
H20: =$I$20/$C$19 -> #REF! | I20: =C19-I18 -> #REF! | J20: NC RESULTANTE
B21: Exchange rate differential
B22: A partir de 18/6

Sheet Breakdown
E4: ='Bahia Blanca'!B5 -> 0
B10: Port dues
C12: =_xlfn.CONCAT("Port ","BAHIA BLANCA"," - Terminal ",'Bahia Blanca'!B10) -> Port BAHIA BLANCA - Terminal
C13: ='Bahia Blanca'!B12 -> 20209 | D13: TRN*0,37* | E13: =_xlfn.CONCAT('Bahia Blanca'!B19," days at port") -> 1,33 days at port | G13: ='Bahia Blanca'!A20 -> 12363.866
F16: TOTAL USD | G16: =G13 -> 12363.866
B21: Toll dues
B22: Includes retribution for the maintenance of external and internal navigation channel depth used for the navigation of the vessel.
D24: TONS X 0.95 X Ft + TONS X 0.40 X Ft
D26: ='Bahia Blanca'!A27 -> 12050 | E26: * 0,95 * | F26: {=_xlfn.IFS('Bahia Blanca'!A27<5000,0.6,'Bahia Blanca'!A27<=10000,0.85,'Bahia Blanca'!A27<=17000,1,'Bahia Blanca'!A27<=30000,1.15)} -> 1 | G26: =_xlfn.CONCAT("* ",D26) -> * 12050 | H26: * 0,4 * | I26: =F26 -> 1 | J26: =_xlfn.CONCAT("= ",'Bahia Blanca'!A28) -> = 28407,875
B28: TONS=Gross tons loading or discharge of the vessel
B29: Ft = Vessel capacity Coefficient ( see chart below)
B31: Coefficient for vessel capacity (Ft):
B33: TRN | F33: Ft
B34: Less than 5.000 | F34: 0.6
B35: More than 5.000 to 10.000 inclusive | F35: 0.85
B36: More than 10.000 to 17.000 inclusive | F36: 1
B37: More than 17.000 to 24.000 inclusive | F37: 1.15
B38: More than 24.000 | F38: 1.15
B42: Bunker operation:
B43: TRN 20% * 1.35 *USD 0.90 * 1.15
B44: Base: Per gross ton or fraction loaded or discharged by the ship, with consideration of the draft and the capacity of the ship.
B49: Port pilotage
B51: Tariffs for entrance or sailing:
B52: B.T. (basic tariff) =( (Fiscal unit tariff 14 * Vessel's Fiscal Coefficient) + (Fiscal unit tariff 8 * Vessel's Fiscal Coefficient) (Fiscal unit tariff 12 * N km travelled )) + % Exceeding draft if more than 28 feets
C55: ( 14 * | D55: =_xlfn.CONCAT('Bahia Blanca'!B11," ) "," + ") -> 150 ) + | E55: ( 8 * | F55: =D55 -> 150 ) + | G55: {=_xlfn.IFS('Bahia Blanca'!B10='Bahia Blanca'!B41,"+ (12 * 53)",'Bahia Blanca'!B10='Bahia Blanca'!D41,"+ (12 * 55)",'Bahia Blanca'!B10='Bahia Blanca'!F41,"+ (12 * 25)")} -> #N/A | H55: * 1,15 | I55: = | J55: USD | K55: =IF('Bahia Blanca'!B10='Bahia Blanca'!B41,'Bahia Blanca'!B42,IF('Bahia Blanca'!B10='Bahia Blanca'!D41,'Bahia Blanca'!D42,IF('Bahia Blanca'!B10='Bahia Blanca'!F41,'Bahia Blanca'!F42,0))) -> 0
B58: Vessel’s Fiscal Coefficient: (Length Overall * Extreme Breadth * Depth Overall)/800
C60: Destination | F60: Km
C61: Buoy 11 - Pto Rosales | F61: 25
C62: Buoy 11 - Ing White | F62: 53
C63: Buoy 11 - Pto Galvan | F63: 55
B66: Connected services ( Transportation + Pilots boats ) | H66: USD 6064

Sheet Calculos
A1: XX
A2: GOLDEN OCEAN GROUP
A3: ADM
A4: AMAGGI
A5: ARASCO
A6: AXLE MARINE SINGAPURE
A7: BALKAN AND BLACK SEA
A8: BALTNAV
A9: BERGE
A10: BOLTEN
A11: CANAL ROJO
A12: CARGILL
... A59: WL MANAGEMENT
